gotit_verify/__init__.py
gotit_verify/apis.py
gotit_verify/exceptions.py
gotit_verify/utils.py
gotit_verify/schemas/__init__.py
gotit_verify-0.0.2.dist-info/LICENSE
gotit_verify-0.0.2.dist-info/METADATA
gotit_verify-0.0.2.dist-info/WHEEL
gotit_verify-0.0.2.dist-info/top_level.txt
gotit_verify-0.0.2.dist-info/RECORD
