Metadata-Version: 2.1
Name: gotit-verify
Version: 0.0.2
Summary: A Verify SDK for confirming identity of GotIt authenticated apps
Home-page: https://github.com/xoxwaw/
Author: Phi Nguyen
Author-email: phi@gotitapp.co
License: UNKNOWN
Platform: UNKNOWN
Classifier: Programming Language :: Python :: 3
Classifier: License :: OSI Approved :: MIT License
Classifier: Operating System :: OS Independent
Requires-Python: >=3.6
Requires-Dist: coverage (==5.2.1)
Requires-Dist: marshmallow (==3.7.1)
Requires-Dist: PyJWT (==1.7.1)
Requires-Dist: pytest (==5.4.3)
Requires-Dist: pytest-cov (==2.10.0)
Requires-Dist: pytest-mock (==3.2.0)
Requires-Dist: python-dotenv (==0.14.0)
Requires-Dist: requests (==2.24.0)
Requires-Dist: requests-mock (==1.8.0)
